cobacoba/Stem.py
cobacoba/__init__.py
cobacoba/lemma.py
cobacoba-1.0.2.dist-info/METADATA
cobacoba-1.0.2.dist-info/WHEEL
cobacoba-1.0.2.dist-info/top_level.txt
cobacoba-1.0.2.dist-info/RECORD
