Metadata-Version: 2.1
Name: cobacoba
Version: 1.0.2
